django_tasks_redis/__init__.py
django_tasks_redis/admin.py
django_tasks_redis/apps.py
django_tasks_redis/backends.py
django_tasks_redis/executor.py
django_tasks_redis/urls.py
django_tasks_redis/utils.py
django_tasks_redis/views.py
django_tasks_redis/management/__init__.py
django_tasks_redis/management/commands/__init__.py
django_tasks_redis/management/commands/purge_completed_redis_tasks.py
django_tasks_redis/management/commands/run_redis_tasks.py
django_tasks_redis-0.1.0.dist-info/licenses/LICENSE
django_tasks_redis-0.1.0.dist-info/METADATA
django_tasks_redis-0.1.0.dist-info/WHEEL
django_tasks_redis-0.1.0.dist-info/top_level.txt
django_tasks_redis-0.1.0.dist-info/RECORD
